Metadata-Version: 1.1
Name: apollo-config
Version: 0.0.3
Summary: apollo_config
Home-page: UNKNOWN
Author: yangxialong
Author-email: nmgcfyxl@163.com
License: UNKNOWN
Platform: any
Classifier: Programming Language :: Python
Classifier: Programming Language :: Python :: 2.7
